pandas_refract.py
pandas_refract-1.2.5.dist-info/LICENSE.txt
pandas_refract-1.2.5.dist-info/METADATA
pandas_refract-1.2.5.dist-info/RECORD
pandas_refract-1.2.5.dist-info/WHEEL
pandas_refract-1.2.5.dist-info/top_level.txt
