Metadata-Version: 2.1
Name: pandas-refract
Version: 1.2.5
Summary: Unofficial convenience functions that deal with fragmenting Pandas dataframes.
Home-page: https://gitlab.com/ittVannak/pandas-refract
Author: Nicholas Lawrence
Author-email: nickclawrence@gmail.com
License: MIT
Platform: UNKNOWN
Classifier: Intended Audience :: Developers
Classifier: Natural Language :: English
Classifier: License :: OSI Approved :: MIT License
Classifier: Operating System :: OS Independent
Classifier: Programming Language :: Python
Classifier: Topic :: Software Development :: Libraries :: Python Modules
Requires-Dist: numpy (>=1.16.2)
